{
    "TargetMetadata": {
      "TargetSchema": "",
      "SupportLobs": true,
      "FullLobMode": false,
      "LobChunkSize": 64,
      "LimitedSizeLobMode": true,
      "LobMaxSize": 32,
      "InlineLobMaxSize": 0,
      "LoadMaxFileSize": 0,
      "ParallelLoadThreads": 0,
      "ParallelLoadBufferSize": 0,
      "BatchApplyEnabled": false,
      "TaskRecoveryTableEnabled": false
    },
    "FullLoadSettings": {
      "TargetTablePrepMode": "DO_NOTHING",
      "CreatePkAfterFullLoad": false,
      "StopTaskCachedChangesApplied": false,
      "StopTaskCachedChangesNotApplied": false,
      "MaxFullLoadSubTasks": 8,
      "TransactionConsistencyTimeout": 600,
      "CommitRate": 10000
    },
    "Logging": {
      "EnableLogging": true
    },
    "ControlTablesSettings": {
      "ControlSchema": ""
    }
  }
  